nulltk/__init__.py
nulltk/color.py
nulltk/colors.py
nulltk/floatingwindow.py
nulltk/graph.py
nulltk/image.py
nulltk/input.py
nulltk/mixins.py
nulltk/overlaywindow.py
nulltk/radialgauge.py
nulltk/style.py
nulltk/styles.py
nulltk/tabbedframe.py
nulltk/textnumbered.py
nulltk/timeplot.py
nulltk/tkroot.py
nulltk/abstract/__init__.py
nulltk/abstract/gauge.py
nulltk-0.0.11.dist-info/LICENSE
nulltk-0.0.11.dist-info/METADATA
nulltk-0.0.11.dist-info/WHEEL
nulltk-0.0.11.dist-info/top_level.txt
nulltk-0.0.11.dist-info/RECORD
