Metadata-Version: 2.1
Name: nulltk
Version: 0.0.11
Summary: A helper library to make tkinter UI easier
Home-page: https://github.com/nhammond129/nulltk
Author: Nicholas Hammond
Author-email: nhammond129@gmail.com
License: UNKNOWN
Project-URL: Bug Tracker, https://github.com/nhammond129/nulltk/issues
Platform: UNKNOWN
Classifier: Programming Language :: Python :: 3
Classifier: License :: OSI Approved :: MIT License
Classifier: Operating System :: OS Independent
Requires-Python: >=3.7
License-File: LICENSE
Requires-Dist: pillow
Requires-Dist: opencv-python
